Workbook
Name _1: FORM5!#REF!
Name _11220: FORM5!#REF!
Name _11310: FORM5!#REF!
Name _11321: FORM5!#REF!
Name _11322: FORM5!#REF!
Name _11324: FORM5!#REF!
Name _11400: FORM5!#REF!
Name _11600: FORM5!#REF!
Name _11700: FORM5!#REF!
Name _11810: FORM5!#REF!
Name _11910: FORM5!#REF!
Name _12100: FORM5!#REF!
Name _13110: FORM5!#REF!
Name _13120: FORM5!#REF!
Name _13131: FORM5!#REF!
Name _13200: FORM5!#REF!
Name _15400: FORM5!#REF!
Name _2: FORM5!#REF!
Name _21100: FORM5!#REF!
Name _21200: FORM5!#REF!
Name _21300: FORM5!#REF!
Name _21400: FORM5!#REF!
Name _21500: FORM5!#REF!
Name _21600: FORM5!#REF!
Name _22110: FORM5!#REF!
Name _22120: FORM5!#REF!
Name _22210: FORM5!#REF!
Name _22220: FORM5!#REF!
Name _22300: FORM5!#REF!
Name _22500: FORM5!#REF!
Name _22600: FORM5!#REF!
Name _23100: FORM5!#REF!
Name _23200: FORM5!#REF!
Name _23400: FORM5!#REF!
Name _24110: FORM5!#REF!
Name _24120: FORM5!#REF!
Name _24130: FORM5!#REF!
Name _24300: FORM5!#REF!
Name _25120: FORM5!#REF!
Name _25210: FORM5!#REF!
Name _25220: FORM5!#REF!
Name _25300: FORM5!#REF!
Name _25400: FORM5!#REF!
Name _25500: FORM5!#REF!
Name _25600: FORM5!#REF!
Name _25700: FORM5!#REF!
Name _25900: FORM5!#REF!
Name _26200: FORM5!#REF!
Name _26610: FORM5!#REF!
Name _26620: FORM5!#REF!
Name _26630: FORM5!#REF!
Name _26990: FORM5!#REF!
Name _3: FORM5!#REF!
Name _31110: FORM5!#REF!
Name _31120: FORM5!#REF!
Name _31140: FORM5!#REF!
Name _32100: FORM5!#REF!
Name _32200: FORM5!#REF!
Name _32300: FORM5!#REF!
Name _32500: FORM5!#REF!

Sheet FORM5
D2: DEPARTAMENTO NACIONAL DE PLANIFICACION - CNS
D3: PLAN OPERATIVO ANUAL 2026 - PROGRAMACIÓN FÍSICO FINANCIERO
D4: REGIONAL/DEPARTAMENTO : REGIONAL (Ver Poa 2025 *)
D5: UNIDAD EJECUTORA : DISTRITAL (Ver Poa 2025 *)
D6: CAT. PROGRAMATICA 2026 : APERTURA - JEFATURA/ESTABLECIMIENTO (Ver Poa 2025 *)
D7: UNIDAD RESPONSABLE : DIRECCION CIMFA/CIS, UNIDAD RESPONSABLE (Ver Poa 2025 *)
B9: N° | C9: COD_ACT | D9: PARTIDA | E9: DESCRIPCIÓN | F9: UNIDAD DE MEDIDA | G9: CANTIDAD | H9: PRECIO UNITARIO | I9: TOTAL PRESUPUESTO | J9: TEMPORALIDAD FINANCIERA | V9: TOTAL FF | X9: OBSERVACION
J10: ENE | K10: FEB | L10: MAR | M10: ABR | N10: MAY | O10: JUN | P10: JUL | Q10: AGO | R10: SEP | S10: OCT | T10: NOV | U10: DIC
B11: 1 | I11: =G11*H11 -> 0 | V11: =SUM(J11:U11) -> 0 | W11: =IF(I11=V11,"P","O") -> P
B12: 2 | I12: =G12*H12 -> 0 | V12: =SUM(J12:U12) -> 0 | W12: =IF(I12=V12,"P","O") -> P
B13: 3 | I13: =G13*H13 -> 0 | V13: =SUM(J13:U13) -> 0 | W13: =IF(I13=V13,"P","O") -> P
B14: 4 | I14: =G14*H14 -> 0 | V14: =SUM(J14:U14) -> 0 | W14: =IF(I14=V14,"P","O") -> P
B15: 5 | I15: =G15*H15 -> 0 | V15: =SUM(J15:U15) -> 0 | W15: =IF(I15=V15,"P","O") -> P
B16: 6 | I16: =G16*H16 -> 0 | V16: =SUM(J16:U16) -> 0 | W16: =IF(I16=V16,"P","O") -> P
B17: 7 | I17: =G17*H17 -> 0 | V17: =SUM(J17:U17) -> 0 | W17: =IF(I17=V17,"P","O") -> P
B18: 8 | I18: =G18*H18 -> 0 | V18: =SUM(J18:U18) -> 0 | W18: =IF(I18=V18,"P","O") -> P
B19: 9 | I19: =G19*H19 -> 0 | V19: =SUM(J19:U19) -> 0 | W19: =IF(I19=V19,"P","O") -> P
B20: 10 | I20: =G20*H20 -> 0 | V20: =SUM(J20:U20) -> 0 | W20: =IF(I20=V20,"P","O") -> P
B21: 11 | I21: =G21*H21 -> 0 | V21: =SUM(J21:U21) -> 0 | W21: =IF(I21=V21,"P","O") -> P
B22: 12 | I22: =G22*H22 -> 0 | V22: =SUM(J22:U22) -> 0 | W22: =IF(I22=V22,"P","O") -> P
... B610: 600 | I610: =G610*H610 -> 0 | V610: =SUM(J610:U610) -> 0 | W610: =IF(I610=V610,"P","O") -> P

Sheet RESUMEN PARTIDAS 2026
A1: PLAN OPERATIVO ANUAL 2026 - PROGRAMACIÓN FÍSICO FINANCIERO
A2: RESUMEN DE PARTIDAS
A3: T O T A L G A S T O S 2026 | D3: =D4+D24+D61+D89+D107+D109+D118+D122 -> 0
A4: 10000 | B4: SERVICIOS PERSONALES | D4: =SUM(D5:D23) -> 0
A5: 11220 | B5: Bono de Antigüedad | D5: =SUMIF(FORM5!D11:D610,"11220",FORM5!I11:I610) -> 0
A6: 11310 | B6: Bono de Frontera | D6: =SUMIF(FORM5!D11:D610,"11310",FORM5!I11:I610) -> 0
A7: 11321 | B7: Categorías Médicas | D7: =SUMIF(FORM5!D11:D610,"11321",FORM5!I11:I610) -> 0
A8: 11322 | B8: Escalafón Médico | D8: =SUMIF(FORM5!D11:D610,"11322",FORM5!I11:I610) -> 0
A9: 11324 | B9: Otras Bonificaciones | D9: =SUMIF(FORM5!D11:D610,"11324",FORM5!I11:I610) -> 0
A10: 11400 | B10: A g u i n a l d o s | D10: =SUMIF(FORM5!D11:D610,"11400",FORM5!I11:I610) -> 0
A11: 11600 | B11: Asignaciones Familiares | D11: =SUMIF(FORM5!D11:D610,"11600",FORM5!I11:I610) -> 0
A12: 11700 | B12: S u e l d o s | D12: =SUMIF(FORM5!D11:D610,"11700",FORM5!I11:I610) -> 0
A13: 11810 | B13: Dietas de Directorio | D13: =SUMIF(FORM5!D11:D610,"11810",FORM5!I11:I610) -> 0
A14: 11910 | B14: Horas Extraordinarias | D14: =SUMIF(FORM5!D11:D610,"11910",FORM5!I11:I610) -> 0
A15: 11920 | B15: Vacaciones No utilizadas | D15: =SUMIF(FORM5!D11:D610,"11920",FORM5!I11:I610) -> 0
A16: 12100 | B16: Personal Eventual | D16: =SUMIF(FORM5!D11:D610,"12100",FORM5!I11:I610) -> 0
A17: 13110 | B17: Regimen de Corto Plazo ( Salud ) | D17: =SUMIF(FORM5!D11:D610,"13110",FORM5!I11:I610) -> 0
A18: 13120 | B18: Prima de Riesgo Profesional - Regimen de Largo Plazo | D18: =SUMIF(FORM5!D11:D610,"13120",FORM5!I11:I610) -> 0
A19: 13131 | B19: Aporte Patronal Solidario 3% | D19: =SUMIF(FORM5!D11:D610,"13131",FORM5!I11:I610) -> 0
A20: 13200 | B20: Aporte Patronal Para Vivienda | D20: =SUMIF(FORM5!D11:D610,"13200",FORM5!I11:I610) -> 0
A21: 15100 | B21: Incremento Salarial | D21: =SUMIF(FORM5!D11:D610,"15100",FORM5!I11:I610) -> 0
A22: 15200 | B22: Crecimiento Vegetativo | D22: =SUMIF(FORM5!D11:D610,"15200",FORM5!I11:I610) -> 0
A23: 15400 | B23: Otras Previsiones | D23: =SUMIF(FORM5!D11:D610,"15400",FORM5!I11:I610) -> 0
A24: 20000 | B24: SERVICIOS NO PERSONALES | D24: =SUM(D25:D60) -> 0
A25: 21100 | B25: Comunicaciones | D25: =SUMIF(FORM5!D11:D610,"21100",FORM5!I11:I610) -> 0
A26: 21200 | B26: Energía Eléctrica | D26: =SUMIF(FORM5!D11:D610,"21200",FORM5!I11:I610) -> 0
A27: 21300 | B27: Agua | D27: =SUMIF(FORM5!D11:D610,"21300",FORM5!I11:I610) -> 0
A28: 21400 | B28: Telefonia | D28: =SUMIF(FORM5!D11:D610,"21400",FORM5!I11:I610) -> 0
A29: 21500 | B29: Gas Domiciliario | D29: =SUMIF(FORM5!D11:D610,"21500",FORM5!I11:I610) -> 0
A30: 21600 | B30: Internet y Otros | D30: =SUMIF(FORM5!D11:D610,"21600",FORM5!I11:I610) -> 0
A31: 22110 | B31: Pasajes al Interior del País | D31: =SUMIF(FORM5!D11:D610,"22110",FORM5!I11:I610) -> 0
A32: 22120 | B32: Pasajes al Exterior del País | D32: =SUMIF(FORM5!D11:D610,"22120",FORM5!I11:I610) -> 0
A33: 22210 | B33: Viáticos por Viajes al Interior del País | D33: =SUMIF(FORM5!D11:D610,"22210",FORM5!I11:I610) -> 0
A34: 22220 | B34: Viáticos por Viajes al Exterior del Ppaís | D34: =SUMIF(FORM5!D11:D610,"22220",FORM5!I11:I610) -> 0
A35: 22300 | B35: Fletes y Almacenamiento | D35: =SUMIF(FORM5!D11:D610,"22300",FORM5!I11:I610) -> 0
A36: 22500 | B36: S e g u r o s | D36: =SUMIF(FORM5!D11:D610,"22500",FORM5!I11:I610) -> 0
A37: 22600 | B37: Transporte de Personal | D37: =SUMIF(FORM5!D11:D610,"22600",FORM5!I11:I610) -> 0
A38: 23100 | B38: Alquiler de Edificios | D38: =SUMIF(FORM5!D11:D610,"23100",FORM5!I11:I610) -> 0
A39: 23200 | B39: Alquiler de Equipos y Maquinarias | D39: =SUMIF(FORM5!D11:D610,"23200",FORM5!I11:I610) -> 0
A40: 23400 | B40: Otros Alquiileres | D40: =SUMIF(FORM5!D11:D610,"23400",FORM5!I11:I610) -> 0
A41: 24110 | B41: Mantenimiento y Reparacion de Inmuebles | D41: =SUMIF(FORM5!D11:D610,"24110",FORM5!I11:I610) -> 0
A42: 24120 | B42: Mantenimiento y Reparacion de Vehículos, Maquinaria y Equipos | D42: =SUMIF(FORM5!D11:D610,"24120",FORM5!I11:I610) -> 0
A43: 24130 | B43: Mantenimiento y Reparacion de Muebles y Enseres | D43: =SUMIF(FORM5!D11:D610,"24130",FORM5!I11:I610) -> 0
A44: 24300 | B44: Otros Gastos por concepto de Instalacion, redes de datos red LAN | D44: =SUMIF(FORM5!D11:D610,"24300",FORM5!I11:I610) -> 0
A45: 25120 | B45: Gastos Especializados Por Atención Médica | D45: =SUMIF(FORM5!D11:D610,"25120",FORM5!I11:I610) -> 0
A46: 25210 | B46: Consultorias Por producto | D46: =SUMIF(FORM5!D11:D610,"25210",FORM5!I11:I610) -> 0
A47: 25220 | B47: Consultores de Línea | D47: =SUMIF(FORM5!D11:D610,"25220",FORM5!I11:I610) -> 0
A48: 25230 | B48: Auditorías Externas | D48: =SUMIF(FORM5!D11:D610,"25230",FORM5!I11:I610) -> 0
A49: 25300 | B49: Comisiones y Gastos Bancarios | D49: =SUMIF(FORM5!D11:D610,"25300",FORM5!I11:I610) -> 0
A50: 25400 | B50: Lavandería, Limpieza é Higiene | D50: =SUMIF(FORM5!D11:D610,"25400",FORM5!I11:I610) -> 0
A51: 25500 | B51: Publicidad | D51: =SUMIF(FORM5!D11:D610,"25500",FORM5!I11:I610) -> 0
A52: 25600 | B52: Servicios de Imprenta y Fotocopiado y Fotográficos | D52: =SUMIF(FORM5!D11:D610,"25600",FORM5!I11:I610) -> 0
A53: 25700 | B53: Capacitación del Personal | D53: =SUMIF(FORM5!D11:D610,"25700",FORM5!I11:I610) -> 0
A54: 25900 | B54: Servicios Manuales | D54: =SUMIF(FORM5!D11:D610,"25900",FORM5!I11:I610) -> 0
A55: 26200 | B55: Gastos Judiciales | D55: =SUMIF(FORM5!D11:D610,"26200",FORM5!I11:I610) -> 0
A56: 26610 | B56: Servicios Públicos | D56: =SUMIF(FORM5!D11:D610,"26610",FORM5!I11:I610) -> 0
A57: 26620 | B57: Servicios Privados | D57: =SUMIF(FORM5!D11:D610,"26620",FORM5!I11:I610) -> 0
A58: 26630 | B58: Servicio Traslado de Valores | D58: =SUMIF(FORM5!D11:D610,"26630",FORM5!I11:I610) -> 0
A59: 26950 | B59: Aguinaldo Esfuerzo por Bolivia | D59: =SUMIF(FORM5!D11:D610,"26950",FORM5!I11:I610) -> 0
A60: 26990 | B60: Otros | D60: =SUMIF(FORM5!D11:D610,"26990",FORM5!I11:I610) -> 0
A61: 30000 | B61: MATERIALES Y SUMINISTROS | D61: =SUM(D62:D88) -> 0
A62: 31110 | B62: Gastos Destinados al Pago de Refrigerios al Personal de Instituciones Públicas | D62: =SUMIF(FORM5!D11:D610,"31110",FORM5!I11:I610) -> 0
A63: 31120 | B63: Gastos por Alimentación y Otros Similares | D63: =SUMIF(FORM5!D11:D610,"31120",FORM5!I11:I610) -> 0
A64: 31140 | B64: Alimentacion Hospitalaria, Penitenciaria, Aeronaves y Otras Específicas | D64: =SUMIF(FORM5!D11:D610,"31140",FORM5!I11:I610) -> 0
A65: 32100 | B65: Papel | D65: =SUMIF(FORM5!D11:D610,"32100",FORM5!I11:I610) -> 0
A66: 32200 | B66: Productos de Artes Gráficas | D66: =SUMIF(FORM5!D11:D610,"32200",FORM5!I11:I610) -> 0
A67: 32300 | B67: Libros Manuales y Revistas | D67: =SUMIF(FORM5!D11:D610,"32300",FORM5!I11:I610) -> 0
A68: 32500 | B68: Periódicos y Boletines | D68: =SUMIF(FORM5!D11:D610,"32500",FORM5!I11:I610) -> 0
A69: 33100 | B69: Hilados y Telas | D69: =SUMIF(FORM5!D11:D610,"33100",FORM5!I11:I610) -> 0
A70: 33200 | B70: Confecciones Textiles | D70: =SUMIF(FORM5!D11:D610,"33200",FORM5!I11:I610) -> 0
A71: 33300 | B71: Prendas de Vestir | D71: =SUMIF(FORM5!D11:D610,"33300",FORM5!I11:I610) -> 0
A72: 33400 | B72: C a l z a d o s | D72: =SUMIF(FORM5!D11:D610,"33400",FORM5!I11:I610) -> 0
A73: 34110 | B73: Combustibles, Lubricantes y Derivados para Consumo | D73: =SUMIF(FORM5!D11:D610,"34110",FORM5!I11:I610) -> 0
A74: 34200 | B74: Productos Quimicos y Farmaceúticos | D74: =SUMIF(FORM5!D11:D610,"34200",FORM5!I11:I610) -> 0
A75: 34300 | B75: Llantas y Neumáticos | D75: =SUMIF(FORM5!D11:D610,"34300",FORM5!I11:I610) -> 0
A76: 34400 | B76: Productos de Cuero y Caucho | D76: =SUMIF(FORM5!D11:D610,"34400",FORM5!I11:I610) -> 0
A77: 34500 | B77: Productos de Minerales no Metálicos y Plásticos | D77: =SUMIF(FORM5!D11:D610,"34500",FORM5!I11:I610) -> 0
A78: 34600 | B78: Productos Metálicos | D78: =SUMIF(FORM5!D11:D610,"34600",FORM5!I11:I610) -> 0
A79: 34800 | B79: Herramientas Menores | D79: =SUMIF(FORM5!D11:D610,"34800",FORM5!I11:I610) -> 0
A80: 39100 | B80: Material de Limpieza | D80: =SUMIF(FORM5!D11:D610,"39100",FORM5!I11:I610) -> 0
A81: 39200 | B81: Material Deportivo y Recreativo | D81: =SUMIF(FORM5!D11:D610,"39200",FORM5!I11:I610) -> 0
A82: 39300 | B82: Utensilios de Cocina y Comedor | D82: =SUMIF(FORM5!D11:D610,"39300",FORM5!I11:I610) -> 0
A83: 39400 | B83: Instrumental Menor Medico-Quirúrgico | D83: =SUMIF(FORM5!D11:D610,"39400",FORM5!I11:I610) -> 0
A84: 39500 | B84: Utiles de Escritorio y Oficina | D84: =SUMIF(FORM5!D11:D610,"39500",FORM5!I11:I610) -> 0
A85: 39600 | B85: Utiles Educacionales, Culturales y de Capacitación | D85: =SUMIF(FORM5!D11:D610,"39600",FORM5!I11:I610) -> 0
A86: 39700 | B86: Utiles y Materiales Eléctricos | D86: =SUMIF(FORM5!D11:D610,"39700",FORM5!I11:I610) -> 0
A87: 39800 | B87: Otros Repuestos y Accesorios | D87: =SUMIF(FORM5!D11:D610,"39800",FORM5!I11:I610) -> 0
A88: 39990 | B88: Otros Materiales y Suministros | D88: =SUMIF(FORM5!D11:D610,"39990",FORM5!I11:I610) -> 0
A89: 40000 | B89: ACTIVOS REALES | D89: =SUM(D90:D106) -> 0
A90: 41100 | B90: Edificios | D90: =SUMIF(FORM5!D11:D610,"41100",FORM5!I11:I610) -> 0
A91: 41200 | B91: Tierras y Terrenos | D91: =SUMIF(FORM5!D11:D610,"41200",FORM5!I11:I610) -> 0
A92: 41300 | B92: Otras Adquisiciones | D92: =SUMIF(FORM5!D11:D610,"41300",FORM5!I11:I610) -> 0
A93: 42230 | B93: Otras Construcciones y Mejoras de Bienes Públicos de Dominio Privado | D93: =SUMIF(FORM5!D11:D610,"42230",FORM5!I11:I610) -> 0
A94: 42240 | B94: Supervicion de Construcciones y Mejoras de Bienes Públicos de Dominio Privado | D94: =SUMIF(FORM5!D11:D610,"42240",FORM5!I11:I610) -> 0
A95: 43110 | B95: Equipo de Oficina y Muebles | D95: =SUMIF(FORM5!D11:D610,"43110",FORM5!I11:I610) -> 0
A96: 43120 | B96: Equipo de Computación | D96: =SUMIF(FORM5!D11:D610,"43120",FORM5!I11:I610) -> 0
A97: 43310 | B97: Vehiculos Livianos para Funciones Administrativas | D97: =SUMIF(FORM5!D11:D610,"43310",FORM5!I11:I610) -> 0
A98: 43330 | B98: Maquinaria y equippo de Transporte de Tracción | D98: =SUMIF(FORM5!D11:D610,"43330",FORM5!I11:I610) -> 0
A99: 43340 | B99: Equipo de Elevación | D99: =SUMIF(FORM5!D11:D610,"43340",FORM5!I11:I610) -> 0
A100: 43400 | B100: Equipo Medico y de Laboratorio | D100: =SUMIF(FORM5!D11:D610,"43400",FORM5!I11:I610) -> 0
...
